notifier/__init__.py
notifier/cli.py
notifier/exceptions.py
notifier/notify.py
notifier/toast.py
notifier/data/example_notification_sound.wav
notifier/data/py-logo.png
notifier/data/python.ico
notifier/os_notifiers/__init__.py
notifier/os_notifiers/_base.py
notifier/os_notifiers/linux.py
notifier/os_notifiers/macos.py
notifier/os_notifiers/windows.py
notifier/os_notifiers/windows_legacy.py
notifier.py-0.4.6.dist-info/LICENSE
notifier.py-0.4.6.dist-info/METADATA
notifier.py-0.4.6.dist-info/WHEEL
notifier.py-0.4.6.dist-info/entry_points.txt
notifier.py-0.4.6.dist-info/top_level.txt
notifier.py-0.4.6.dist-info/RECORD
