Metadata-Version: 2.1
Name: notifier.py
Version: 0.4.6
Summary: A simple Python library that simplifies the sending of desktop notifications!
Home-page: https://github.com/Strawberry-Foundations/notifier
Author: Juliandev02
Classifier: Programming Language :: Python :: 3
Classifier: License :: OSI Approved :: MIT License
Classifier: Operating System :: OS Independent
Requires-Python: >=3.6.0
License-File: LICENSE
Requires-Dist: loguru
Requires-Dist: jeepney ; platform_system == "Linux"
